[  
   {  
      "widget_id":"1",
      "title":"",
      "page_id":"2",
      "dataSource" : {
                    "name" : "osian",
                    "config" : 
                            {
                                "site":"//staging.osianama.com/",
                                "resource":"homepage"
                            }
                    },
      "renderer_name":"grid",
      "params":""
   },
   {  
      "widget_id":"2",
      "title":"Countries",
      "page_id":"1",
      "dataSource" : {
            "name" : "countries",
            "config" : {
                "type" : "chekcing config"
            }
        },
      "renderer_name":"grid",
      "params":""
   },
   {  
      "widget_id":"3",
      "title":"Users",
      "page_id":"2",
      "dataSource" : {
            "name" : "",
            "config" : { }
        },
       "renderer_name":"carousel",
       "params":""
   },
   {  
      "widget_id":"4",
      "title":"Todos",
      "page_id":"2",
      "dataSource" : {
                "name" : "",
                "config" : { }
        },
      "renderer_name":"",
      "params":""
   },
   {  
      "widget_id":"5",
      "title":"Widget 5",
      "page_id":"3",
      "dataSource" : {
            "name" : "",
            "config" : { }
        },
      "renderer_name":"",
      "params":""
   },
   {  
      "widget_id":"6",
      "title":"Widget 6",
      "page_id":"3",
      "dataSource" : {
        "name" : "",
        "config" : { }
        },
      "renderer_name":"",
      "params":""
   }
]
